paddlelite-2.12.data/purelib/paddlelite/__init__.py
paddlelite-2.12.data/purelib/paddlelite/lite.so
paddlelite-2.12.data/purelib/paddlelite/libs/libiomp5.so
paddlelite-2.12.data/purelib/paddlelite/libs/libmklml_intel.so
paddlelite-2.12.data/scripts/paddle_lite_opt
paddlelite-2.12.dist-info/METADATA
paddlelite-2.12.dist-info/WHEEL
paddlelite-2.12.dist-info/top_level.txt
paddlelite-2.12.dist-info/RECORD
