Metadata-Version: 2.1
Name: paddlelite
Version: 2.12
Summary: Paddle-Lite Library
Home-page: UNKNOWN
Author: UNKNOWN
Author-email: UNKNOWN
License: UNKNOWN
Platform: UNKNOWN
